[{"eventType":"Uebung","titleShort":"BWL1 Ü","_id":"4edc85b7e4b090a2379d239f","member":[{"fhs_id":"","name":"Carjell"}],"className":"bawi1","titleLong":"","appointment":{"day":"Montag","location":{"place":{"building":"H","room":"0203"},"alternative":[]},"time":"08.15-09.45","week":"w"},"group":""},{"eventType":"Vorlesung","titleShort":"Alg/GrMa1V","_id":"4edc85b7e4b090a2379d23a0","member":[{"fhs_id":"","name":"Recknagel"}],"className":"bawi1","titleLong":"","appointment":{"day":"Dienstag","location":{"place":{"building":"H","room":"0002"},"alternative":[]},"time":"08.15-09.45","week":"g"},"group":" "},{"eventType":"Uebung","titleShort":"PP-DSA Ü","_id":"4edc85b7e4b090a2379d23a1","member":[{"fhs_id":"","name":"Recknagel"}],"className":"bawi1","titleLong":"","appointment":{"day":"Freitag","location":{"place":{"building":"B","room":"PC1"},"alternative":[]},"time":"08.15-09.45","week":"u"},"group":" 1"},{"eventType":"Uebung","titleShort":"PP-DSA Ü","_id":"4edc85b7e4b090a2379d23a2","member":[{"fhs_id":"","name":"Recknagel"}],"className":"bawi1","titleLong":"","appointment":{"day":"Freitag","location":{"place":{"building":"B","room":"PC1"},"alternative":[]},"time":"08.15-09.45","week":"g"},"group":" 2"},{"eventType":"Uebung","titleShort":"PP-DSA Ü","_id":"4edc85b7e4b090a2379d23a3","member":[{"fhs_id":"","name":"Recknagel"}],"className":"bawi1","titleLong":"","appointment":{"day":"Dienstag","location":{"place":{"building":"B","room":"PC1"},"alternative":[]},"time":"10.00-11.30","week":"w"},"group":"1"},{"eventType":"Vorlesung","titleShort":"PP-DSA","_id":"4edc85b7e4b090a2379d23a4","member":[{"fhs_id":"","name":"BeyerBraun"}],"className":"bawi1","titleLong":"","appointment":{"day":"Mittwoch","location":{"place":{"building":"H","room":"0202"},"alternative":[]},"time":"10.00-11.30","week":"w"},"group":""},{"eventType":"Uebung","titleShort":"PP-DSA Ü","_id":"4edc85b7e4b090a2379d23a5","member":[{"fhs_id":"","name":"Recknagel"}],"className":"bawi1","titleLong":"","appointment":{"day":"Freitag","location":{"place":{"building":"B","room":"PC1"},"alternative":[]},"time":"10.00-11.30","week":"g"},"group":" 1"},{"eventType":"Uebung","titleShort":"PP-DSA Ü","_id":"4edc85b7e4b090a2379d23a6","member":[{"fhs_id":"","name":"Recknagel"}],"className":"bawi1","titleLong":"","appointment":{"day":"Freitag","location":{"place":{"building":"B","room":"PC1"},"alternative":[]},"time":"10.00-11.30","week":"u"},"group":" 2"},{"eventType":"Vorlesung","titleShort":"Alg/GrMa1V","_id":"4edc85b7e4b090a2379d23a7","member":[{"fhs_id":"","name":"Recknagel"}],"className":"bawi1","titleLong":"","appointment":{"day":"Montag","location":{"place":{"building":"H","room":"0203"},"alternative":[]},"time":"11.45-13.15","week":"w"},"group":""},{"eventType":"Uebung","titleShort":"PP-DSA Ü","_id":"4edc85b7e4b090a2379d23a8","member":[{"fhs_id":"","name":"Recknagel"}],"className":"bawi1","titleLong":"","appointment":{"day":"Dienstag","location":{"place":{"building":"B","room":"PC1"},"alternative":[]},"time":"11.45-13.15","week":"w"},"group":"2"},{"eventType":"Vorlesung","titleShort":"BWL I V","_id":"4edc85b7e4b090a2379d23a9","member":[{"fhs_id":"","name":"Urban"}],"className":"bawi1","titleLong":"","appointment":{"day":"Mittwoch","location":{"place":{"building":"H","room":"0002"},"alternative":[]},"time":"11.45-13.15","week":"w"},"group":""},{"eventType":"Vorlesung","titleShort":"EinfWI","_id":"4edc85b7e4b090a2379d23aa","member":[{"fhs_id":"","name":"Polster"}],"className":"bawi1","titleLong":"","appointment":{"day":"Freitag","location":{"place":{"building":"H","room":"0003"},"alternative":[]},"time":"11.45-13.15","week":"w"},"group":""},{"eventType":"Vorlesung","titleShort":"ReWe1","_id":"4edc85b7e4b090a2379d23ab","member":[{"fhs_id":"","name":"Jacob"}],"className":"bawi1","titleLong":"","appointment":{"day":"Montag","location":{"place":{"building":"H","room":"0002"},"alternative":[]},"time":"14.15-15.45","week":"w"},"group":""},{"eventType":"Vorlesung","titleShort":"PP-DSA","_id":"4edc85b7e4b090a2379d23ac","member":[{"fhs_id":"","name":"BeyerBraun"}],"className":"bawi1","titleLong":"","appointment":{"day":"Dienstag","location":{"place":{"building":"H","room":"0202"},"alternative":[]},"time":"14.15-15.45","week":"w"},"group":""},{"eventType":"Vorlesung","titleShort":"EinfWI","_id":"4edc85b7e4b090a2379d23ad","member":[{"fhs_id":"","name":"Polster"}],"className":"bawi1","titleLong":"","appointment":{"day":"Freitag","location":{"place":{"building":"H","room":"0003"},"alternative":[]},"time":"14.15-15.45","week":"g"},"group":" "},{"eventType":"Uebung","titleShort":"EinfWI","_id":"4edc85b7e4b090a2379d23ae","member":[{"fhs_id":"","name":"Polster"}],"className":"bawi1","titleLong":"","appointment":{"day":"Freitag","location":{"place":{"building":"H","room":"0003"},"alternative":[]},"time":"14.15-15.45","week":"u"},"group":" "},{"eventType":"Vorlesung","titleShort":"Statistik","_id":"4edc85b7e4b090a2379d23af","member":[{"fhs_id":"","name":"Kleekamp"}],"className":"bawi1","titleLong":"","appointment":{"day":"Dienstag","location":{"place":{"building":"H","room":"0202"},"alternative":[]},"time":"16.00-17.30","week":"w"},"group":""},{"eventType":"Uebung","titleShort":"GrMa1 Ü","_id":"4edc85b7e4b090a2379d23b0","member":[{"fhs_id":"","name":"Recknagel"}],"className":"bawi1","titleLong":"","appointment":{"day":"Montag","location":{"place":{"building":"H","room":"0216"},"alternative":[]},"time":"17.45-19.15","week":"u"},"group":" "},{"eventType":"Uebung","titleShort":"Statistik","_id":"4edc85b7e4b090a2379d23b1","member":[{"fhs_id":"","name":"Kleekamp"}],"className":"bawi1","titleLong":"","appointment":{"day":"Dienstag","location":{"place":{"building":"B","room":"PC1"},"alternative":[]},"time":"17.45-19.15","week":"g"},"group":" 1"},{"eventType":"Uebung","titleShort":"Statistik","_id":"4edc85b7e4b090a2379d23b2","member":[{"fhs_id":"","name":"Kleekamp"}],"className":"bawi1","titleLong":"","appointment":{"day":"Dienstag","location":{"place":{"building":"B","room":"PC1"},"alternative":[]},"time":"17.45-19.15","week":"u"},"group":" 2"}]